roots/__init__.py
roots/core.py
roots/graphmethods.py
roots/kmd.py
roots/microstructures.py
roots/root2neuron.py
roots/swcToolkit.py
roots/visualization.py
Roots-0.0.4.dist-info/LICENSE
Roots-0.0.4.dist-info/METADATA
Roots-0.0.4.dist-info/WHEEL
Roots-0.0.4.dist-info/top_level.txt
Roots-0.0.4.dist-info/RECORD
