Metadata-Version: 2.1
Name: Roots
Version: 0.0.4
Summary: Grows artificial axon arbors based on morphometrics extracted from full axon reconstructions.
Home-page: UNKNOWN
Author: Clayton Bingham
Author-email: clayton.bingham@gmail.com
Maintainer: Clayton Bingham
Maintainer-email: clayton.bingham@gmail.com
License: MIT
Download-URL: https://github.com/bingsome/Roots.git
Platform: UNKNOWN
Requires-Dist: numpy
Requires-Dist: matplotlib
Requires-Dist: networkx
Requires-Dist: mayavi
Requires-Dist: scipy
Requires-Dist: scikit-learn
